Metadata-Version: 1.0
Name: dsnd-probability-jvil
Version: 0.1
Summary: Gaussian and Binomial distributions
Home-page: UNKNOWN
Author: Jed Villareal
Author-email: jedmarievillareal@gmail.com
License: UNKNOWN
Platform: UNKNOWN
